{
  "timestamp": 1775145511,
  "spot": 6563.73,
  "regime": "PIN",
  "totalGex": 105622637017,
  "totalCallGex": 305827754051,
  "totalPutGex": -200205117035,
  "flipStrike": 6562,
  "maxPosStrike": 6580,
  "maxPosGex": 21889139674,
  "maxNegStrike": 6500,
  "maxNegGex": -6164496189,
  "pctChange1m": -20,
  "pctChange5m": -7.2,
  "walls": [
    {
      "strike": 6580,
      "callGex": 29115823712,
      "putGex": -7226684038,
      "netGex": 21889139674,
      "callOI": 54006,
      "putOI": 18268,
      "direction": "stabilizing"
    },
    {
      "strike": 6590,
      "callGex": 14784010090,
      "putGex": -1552055136,
      "netGex": 13231954954,
      "callOI": 44167,
      "putOI": 10047,
      "direction": "stabilizing"
    },
    {
      "strike": 6585,
      "callGex": 13869193761,
      "putGex": -2290102952,
      "netGex": 11579090808,
      "callOI": 32472,
      "putOI": 9310,
      "direction": "stabilizing"
    },
    {
      "strike": 6565,
      "callGex": 21478189995,
      "putGex": -10168190492,
      "netGex": 11309999503,
      "callOI": 33454,
      "putOI": 18898,
      "direction": "stabilizing"
    },
    {
      "strike": 6575,
      "callGex": 25585802792,
      "putGex": -15935669008,
      "netGex": 9650133784,
      "callOI": 52644,
      "putOI": 48782,
      "direction": "stabilizing"
    },
    {
      "strike": 6600,
      "callGex": 16466952843,
      "putGex": -6854175645,
      "netGex": 9612777198,
      "callOI": 180552,
      "putOI": 158997,
      "direction": "stabilizing"
    },
    {
      "strike": 6570,
      "callGex": 24433398511,
      "putGex": -15685229829,
      "netGex": 8748168682,
      "callOI": 40025,
      "putOI": 26906,
      "direction": "stabilizing"
    },
    {
      "strike": 6560,
      "callGex": 21594872846,
      "putGex": -13372249796,
      "netGex": 8222623050,
      "callOI": 35719,
      "putOI": 24544,
      "direction": "stabilizing"
    },
    {
      "strike": 6555,
      "callGex": 14589709992,
      "putGex": -7167295915,
      "netGex": 7422414078,
      "callOI": 24313,
      "putOI": 13531,
      "direction": "stabilizing"
    },
    {
      "strike": 6500,
      "callGex": 3546749662,
      "putGex": -9711245851,
      "netGex": -6164496189,
      "callOI": 101835,
      "putOI": 257495,
      "direction": "amplifying"
    }
  ],
  "strikes": [
    {
      "strike": 6240,
      "netGex": -8343322,
      "callGex": 2151067,
      "putGex": -10494388
    },
    {
      "strike": 6250,
      "netGex": -255966997,
      "callGex": 26926626,
      "putGex": -282893624
    },
    {
      "strike": 6260,
      "netGex": -19208606,
      "callGex": 172797,
      "putGex": -19381403
    },
    {
      "strike": 6270,
      "netGex": -8371775,
      "callGex": 117112,
      "putGex": -8488888
    },
    {
      "strike": 6275,
      "netGex": -322223564,
      "callGex": 14277375,
      "putGex": -336500939
    },
    {
      "strike": 6280,
      "netGex": -10142027,
      "callGex": 1373508,
      "putGex": -11515535
    },
    {
      "strike": 6290,
      "netGex": -6924669,
      "callGex": 250942,
      "putGex": -7175611
    },
    {
      "strike": 6300,
      "netGex": -553493066,
      "callGex": 203428487,
      "putGex": -756921554
    },
    {
      "strike": 6310,
      "netGex": -5530168,
      "callGex": 189997,
      "putGex": -5720165
    },
    {
      "strike": 6320,
      "netGex": -7194966,
      "callGex": 1092728,
      "putGex": -8287694
    },
    {
      "strike": 6325,
      "netGex": -99525158,
      "callGex": 67733500,
      "putGex": -167258658
    },
    {
      "strike": 6330,
      "netGex": -9442804,
      "callGex": 1017930,
      "putGex": -10460734
    },
    {
      "strike": 6340,
      "netGex": -8181498,
      "callGex": 1465367,
      "putGex": -9646865
    },
    {
      "strike": 6350,
      "netGex": -243632531,
      "callGex": 114460148,
      "putGex": -358092679
    },
    {
      "strike": 6360,
      "netGex": -3034093,
      "callGex": 15792060,
      "putGex": -18826152
    },
    {
      "strike": 6365,
      "netGex": -175945563,
      "callGex": 27203325,
      "putGex": -203148889
    },
    {
      "strike": 6370,
      "netGex": -223695686,
      "callGex": 58916718,
      "putGex": -282612405
    },
    {
      "strike": 6375,
      "netGex": -813729880,
      "callGex": 166066669,
      "putGex": -979796549
    },
    {
      "strike": 6380,
      "netGex": -382954340,
      "callGex": 56546825,
      "putGex": -439501164
    },
    {
      "strike": 6385,
      "netGex": -59025788,
      "callGex": 55416767,
      "putGex": -114442556
    },
    {
      "strike": 6390,
      "netGex": -285403568,
      "callGex": 67875048,
      "putGex": -353278616
    },
    {
      "strike": 6395,
      "netGex": -88595585,
      "callGex": 31566528,
      "putGex": -120162113
    },
    {
      "strike": 6400,
      "netGex": -3909867582,
      "callGex": 1394578734,
      "putGex": -5304446316
    },
    {
      "strike": 6405,
      "netGex": -70478026,
      "callGex": 55210454,
      "putGex": -125688480
    },
    {
      "strike": 6410,
      "netGex": -77656769,
      "callGex": 113663577,
      "putGex": -191320346
    },
    {
      "strike": 6415,
      "netGex": -82972001,
      "callGex": 70197244,
      "putGex": -153169245
    },
    {
      "strike": 6420,
      "netGex": -198803680,
      "callGex": 140787915,
      "putGex": -339591595
    },
    {
      "strike": 6425,
      "netGex": -729859646,
      "callGex": 332616556,
      "putGex": -1062476203
    },
    {
      "strike": 6430,
      "netGex": -438737803,
      "callGex": 179757656,
      "putGex": -618495459
    },
    {
      "strike": 6435,
      "netGex": -79249802,
      "callGex": 129345604,
      "putGex": -208595407
    },
    {
      "strike": 6440,
      "netGex": -277556212,
      "callGex": 99150352,
      "putGex": -376706563
    },
    {
      "strike": 6445,
      "netGex": -94513461,
      "callGex": 96465745,
      "putGex": -190979206
    },
    {
      "strike": 6450,
      "netGex": -1860720664,
      "callGex": 1185464357,
      "putGex": -3046185021
    },
    {
      "strike": 6455,
      "netGex": -148408491,
      "callGex": 97313475,
      "putGex": -245721966
    },
    {
      "strike": 6460,
      "netGex": -571385802,
      "callGex": 218839872,
      "putGex": -790225674
    },
    {
      "strike": 6465,
      "netGex": -297960227,
      "callGex": 111625202,
      "putGex": -409585429
    },
    {
      "strike": 6470,
      "netGex": -663357677,
      "callGex": 228703726,
      "putGex": -892061404
    },
    {
      "strike": 6475,
      "netGex": -1163920958,
      "callGex": 415478802,
      "putGex": -1579399761
    },
    {
      "strike": 6480,
      "netGex": -453295132,
      "callGex": 324167424,
      "putGex": -777462556
    },
    {
      "strike": 6485,
      "netGex": -363254770,
      "callGex": 209504684,
      "putGex": -572759455
    },
    {
      "strike": 6490,
      "netGex": -958696450,
      "callGex": 292967107,
      "putGex": -1251663558
    },
    {
      "strike": 6495,
      "netGex": -563568472,
      "callGex": 305169239,
      "putGex": -868737712
    },
    {
      "strike": 6500,
      "netGex": -6164496189,
      "callGex": 3546749662,
      "putGex": -9711245851
    },
    {
      "strike": 6505,
      "netGex": -643255815,
      "callGex": 759063367,
      "putGex": -1402319183
    },
    {
      "strike": 6510,
      "netGex": -1342584260,
      "callGex": 1387720086,
      "putGex": -2730304347
    },
    {
      "strike": 6515,
      "netGex": -944750351,
      "callGex": 1566361802,
      "putGex": -2511112153
    },
    {
      "strike": 6520,
      "netGex": -1520147174,
      "callGex": 2707318574,
      "putGex": -4227465748
    },
    {
      "strike": 6525,
      "netGex": -1643402635,
      "callGex": 4291388455,
      "putGex": -5934791089
    },
    {
      "strike": 6530,
      "netGex": -930301484,
      "callGex": 6149788025,
      "putGex": -7080089509
    },
    {
      "strike": 6535,
      "netGex": 806446720,
      "callGex": 5486695860,
      "putGex": -4680249140
    },
    {
      "strike": 6540,
      "netGex": 445629567,
      "callGex": 8884338437,
      "putGex": -8438708869
    },
    {
      "strike": 6545,
      "netGex": 6149361990,
      "callGex": 14088773757,
      "putGex": -7939411767
    },
    {
      "strike": 6550,
      "netGex": 3015817952,
      "callGex": 23419844337,
      "putGex": -20404026385
    },
    {
      "strike": 6555,
      "netGex": 7422414078,
      "callGex": 14589709992,
      "putGex": -7167295915
    },
    {
      "strike": 6560,
      "netGex": 8222623050,
      "callGex": 21594872846,
      "putGex": -13372249796
    },
    {
      "strike": 6565,
      "netGex": 11309999503,
      "callGex": 21478189995,
      "putGex": -10168190492
    },
    {
      "strike": 6570,
      "netGex": 8748168682,
      "callGex": 24433398511,
      "putGex": -15685229829
    },
    {
      "strike": 6575,
      "netGex": 9650133784,
      "callGex": 25585802792,
      "putGex": -15935669008
    },
    {
      "strike": 6580,
      "netGex": 21889139674,
      "callGex": 29115823712,
      "putGex": -7226684038
    },
    {
      "strike": 6585,
      "netGex": 11579090808,
      "callGex": 13869193761,
      "putGex": -2290102952
    },
    {
      "strike": 6590,
      "netGex": 13231954954,
      "callGex": 14784010090,
      "putGex": -1552055136
    },
    {
      "strike": 6595,
      "netGex": 6139670329,
      "callGex": 7548665509,
      "putGex": -1408995180
    },
    {
      "strike": 6600,
      "netGex": 9612777198,
      "callGex": 16466952843,
      "putGex": -6854175645
    },
    {
      "strike": 6605,
      "netGex": 3883579038,
      "callGex": 4255486375,
      "putGex": -371907336
    },
    {
      "strike": 6610,
      "netGex": 1974802651,
      "callGex": 2381699292,
      "putGex": -406896641
    },
    {
      "strike": 6615,
      "netGex": 938613544,
      "callGex": 1144744217,
      "putGex": -206130673
    },
    {
      "strike": 6620,
      "netGex": 836805201,
      "callGex": 1201251322,
      "putGex": -364446120
    },
    {
      "strike": 6625,
      "netGex": 470969957,
      "callGex": 1379451035,
      "putGex": -908481078
    },
    {
      "strike": 6630,
      "netGex": 231630992,
      "callGex": 761428861,
      "putGex": -529797869
    },
    {
      "strike": 6635,
      "netGex": 242913263,
      "callGex": 472674847,
      "putGex": -229761584
    },
    {
      "strike": 6640,
      "netGex": 196949219,
      "callGex": 596142177,
      "putGex": -399192957
    },
    {
      "strike": 6645,
      "netGex": 139361411,
      "callGex": 355785268,
      "putGex": -216423857
    },
    {
      "strike": 6650,
      "netGex": 728247121,
      "callGex": 3269302707,
      "putGex": -2541055586
    },
    {
      "strike": 6655,
      "netGex": 88950101,
      "callGex": 309373940,
      "putGex": -220423839
    },
    {
      "strike": 6660,
      "netGex": 278254700,
      "callGex": 494425332,
      "putGex": -216170632
    },
    {
      "strike": 6665,
      "netGex": 143794216,
      "callGex": 288777558,
      "putGex": -144983342
    },
    {
      "strike": 6670,
      "netGex": 449664649,
      "callGex": 639172881,
      "putGex": -189508233
    },
    {
      "strike": 6675,
      "netGex": 52037251,
      "callGex": 1006148502,
      "putGex": -954111251
    },
    {
      "strike": 6680,
      "netGex": 209116983,
      "callGex": 526342689,
      "putGex": -317225707
    },
    {
      "strike": 6685,
      "netGex": 182317260,
      "callGex": 285265608,
      "putGex": -102948348
    },
    {
      "strike": 6690,
      "netGex": 978856511,
      "callGex": 1219778472,
      "putGex": -240921961
    },
    {
      "strike": 6695,
      "netGex": 47667973,
      "callGex": 186623545,
      "putGex": -138955572
    },
    {
      "strike": 6700,
      "netGex": 884039284,
      "callGex": 5248150801,
      "putGex": -4364111517
    },
    {
      "strike": 6705,
      "netGex": 155698891,
      "callGex": 217770961,
      "putGex": -62072070
    },
    {
      "strike": 6710,
      "netGex": 329313715,
      "callGex": 543719235,
      "putGex": -214405520
    },
    {
      "strike": 6715,
      "netGex": 182246177,
      "callGex": 272306175,
      "putGex": -90059997
    },
    {
      "strike": 6720,
      "netGex": 138924251,
      "callGex": 386651704,
      "putGex": -247727453
    },
    {
      "strike": 6725,
      "netGex": 42482901,
      "callGex": 1070215386,
      "putGex": -1027732485
    },
    {
      "strike": 6730,
      "netGex": 274404206,
      "callGex": 456474961,
      "putGex": -182070754
    },
    {
      "strike": 6735,
      "netGex": 191343471,
      "callGex": 305603355,
      "putGex": -114259884
    },
    {
      "strike": 6740,
      "netGex": 236222908,
      "callGex": 441119786,
      "putGex": -204896878
    },
    {
      "strike": 6745,
      "netGex": 36350103,
      "callGex": 129367849,
      "putGex": -93017746
    },
    {
      "strike": 6750,
      "netGex": 903295319,
      "callGex": 3226701450,
      "putGex": -2323406132
    },
    {
      "strike": 6755,
      "netGex": 117357856,
      "callGex": 245734107,
      "putGex": -128376251
    },
    {
      "strike": 6760,
      "netGex": 251075872,
      "callGex": 445086718,
      "putGex": -194010846
    },
    {
      "strike": 6770,
      "netGex": 55306108,
      "callGex": 74743105,
      "putGex": -19436997
    },
    {
      "strike": 6775,
      "netGex": 162082775,
      "callGex": 385585284,
      "putGex": -223502509
    },
    {
      "strike": 6780,
      "netGex": 64244016,
      "callGex": 79456966,
      "putGex": -15212950
    },
    {
      "strike": 6790,
      "netGex": 39251351,
      "callGex": 51938375,
      "putGex": -12687024
    },
    {
      "strike": 6800,
      "netGex": 331061028,
      "callGex": 1270548158,
      "putGex": -939487130
    },
    {
      "strike": 6810,
      "netGex": 29243646,
      "callGex": 37401949,
      "putGex": -8158303
    },
    {
      "strike": 6820,
      "netGex": 16234386,
      "callGex": 23571664,
      "putGex": -7337278
    },
    {
      "strike": 6825,
      "netGex": 138666940,
      "callGex": 291269762,
      "putGex": -152602823
    },
    {
      "strike": 6830,
      "netGex": 9899532,
      "callGex": 16862594,
      "putGex": -6963062
    },
    {
      "strike": 6840,
      "netGex": 24064512,
      "callGex": 33267012,
      "putGex": -9202500
    },
    {
      "strike": 6850,
      "netGex": 225139147,
      "callGex": 709618471,
      "putGex": -484479324
    },
    {
      "strike": 6860,
      "netGex": -6237148,
      "callGex": 6548927,
      "putGex": -12786075
    },
    {
      "strike": 6870,
      "netGex": 6943669,
      "callGex": 10129628,
      "putGex": -3185960
    },
    {
      "strike": 6875,
      "netGex": 268721570,
      "callGex": 391954720,
      "putGex": -123233150
    },
    {
      "strike": 6880,
      "netGex": -3240598,
      "callGex": 4074417,
      "putGex": -7315014
    },
    {
      "strike": 6890,
      "netGex": 4507989,
      "callGex": 8294243,
      "putGex": -3786254
    }
  ],
  "events": [
    "wall_break",
    "gex_surge"
  ],
  "commentary": "**DEALER HEDGING COMMENTARY:**\n\nDealers are actively buying the dip right now as SPX trades just above the 6562 flip strike in PIN regime, with the massive 21.9B gamma wall at 6580 acting as a magnet for mean reversion. The recent wall break and GEX surge indicate heavy options flow, but the thick positive gamma cushion from 6565-6590 should cap volatility and drive price action back toward the 6580 max gamma strike. Watch for continued dealer buying support on any test of 6560-6562, while expecting selling pressure to intensify on any push toward the 6580-6590 gamma cluster.",
  "updatedAt": "2026-04-02T15:58:31.608Z",
  "expiry": "2026-04-02:0",
  "expiryCount": 54,
  "dte": 0,
  "commentaryAt": "2026-04-02T15:58:38.807Z"
}