{
  "timestamp": 1779472026,
  "spot": 7496.22,
  "regime": "PIN",
  "totalGex": 110061515868,
  "totalCallGex": 168688278177,
  "totalPutGex": -58626762309,
  "flipStrike": 7397,
  "maxPosStrike": 7500,
  "maxPosGex": 20624259968,
  "maxNegStrike": 7355,
  "maxNegGex": -330275294,
  "pctChange1m": -0.5,
  "pctChange5m": -1.4,
  "walls": [
    {
      "strike": 7500,
      "callGex": 26804188267,
      "putGex": -6179928299,
      "netGex": 20624259968,
      "callOI": 213508,
      "putOI": 99393,
      "direction": "stabilizing"
    },
    {
      "strike": 7600,
      "callGex": 8613368936,
      "putGex": -1105506210,
      "netGex": 7507862726,
      "callOI": 149484,
      "putOI": 28038,
      "direction": "stabilizing"
    },
    {
      "strike": 7450,
      "callGex": 7769423567,
      "putGex": -3002013823,
      "netGex": 4767409743,
      "callOI": 102330,
      "putOI": 39832,
      "direction": "stabilizing"
    },
    {
      "strike": 7525,
      "callGex": 5240488910,
      "putGex": -682393921,
      "netGex": 4558094989,
      "callOI": 44652,
      "putOI": 9200,
      "direction": "stabilizing"
    },
    {
      "strike": 7550,
      "callGex": 5041773644,
      "putGex": -601000766,
      "netGex": 4440772878,
      "callOI": 65431,
      "putOI": 15346,
      "direction": "stabilizing"
    },
    {
      "strike": 7650,
      "callGex": 3738157186,
      "putGex": -161044407,
      "netGex": 3577112780,
      "callOI": 73339,
      "putOI": 5566,
      "direction": "stabilizing"
    },
    {
      "strike": 7475,
      "callGex": 5518786855,
      "putGex": -1955787752,
      "netGex": 3562999103,
      "callOI": 45993,
      "putOI": 19377,
      "direction": "stabilizing"
    },
    {
      "strike": 7505,
      "callGex": 3815400215,
      "putGex": -300939705,
      "netGex": 3514460511,
      "callOI": 7290,
      "putOI": 1752,
      "direction": "stabilizing"
    },
    {
      "strike": 7520,
      "callGex": 3442884415,
      "putGex": -385953143,
      "netGex": 3056931273,
      "callOI": 15291,
      "putOI": 4439,
      "direction": "stabilizing"
    },
    {
      "strike": 7510,
      "callGex": 3394289074,
      "putGex": -489306230,
      "netGex": 2904982844,
      "callOI": 14623,
      "putOI": 3245,
      "direction": "stabilizing"
    }
  ],
  "strikes": [
    {
      "strike": 7125,
      "netGex": -14629317,
      "callGex": 116262775,
      "putGex": -130892092
    },
    {
      "strike": 7150,
      "netGex": 49009696,
      "callGex": 307242186,
      "putGex": -258232491
    },
    {
      "strike": 7160,
      "netGex": -5579632,
      "callGex": 950750,
      "putGex": -6530382
    },
    {
      "strike": 7170,
      "netGex": -2742849,
      "callGex": 3291481,
      "putGex": -6034330
    },
    {
      "strike": 7175,
      "netGex": -138019234,
      "callGex": 123226037,
      "putGex": -261245271
    },
    {
      "strike": 7180,
      "netGex": -3206482,
      "callGex": 1366917,
      "putGex": -4573399
    },
    {
      "strike": 7190,
      "netGex": -6984635,
      "callGex": 472136,
      "putGex": -7456770
    },
    {
      "strike": 7200,
      "netGex": -58267931,
      "callGex": 986961684,
      "putGex": -1045229615
    },
    {
      "strike": 7210,
      "netGex": -8425239,
      "callGex": 1255379,
      "putGex": -9680618
    },
    {
      "strike": 7220,
      "netGex": -4174784,
      "callGex": 1465551,
      "putGex": -5640334
    },
    {
      "strike": 7225,
      "netGex": -44088935,
      "callGex": 144935147,
      "putGex": -189024082
    },
    {
      "strike": 7230,
      "netGex": -9995796,
      "callGex": 2775756,
      "putGex": -12771551
    },
    {
      "strike": 7240,
      "netGex": -9195418,
      "callGex": 370042,
      "putGex": -9565459
    },
    {
      "strike": 7250,
      "netGex": 125351077,
      "callGex": 475277650,
      "putGex": -349926573
    },
    {
      "strike": 7260,
      "netGex": -36337899,
      "callGex": 4623512,
      "putGex": -40961411
    },
    {
      "strike": 7270,
      "netGex": -13015292,
      "callGex": 4106845,
      "putGex": -17122137
    },
    {
      "strike": 7275,
      "netGex": -23806933,
      "callGex": 108407738,
      "putGex": -132214672
    },
    {
      "strike": 7280,
      "netGex": -15837699,
      "callGex": 19797973,
      "putGex": -35635672
    },
    {
      "strike": 7290,
      "netGex": -11737348,
      "callGex": 13844464,
      "putGex": -25581812
    },
    {
      "strike": 7295,
      "netGex": 734504,
      "callGex": 734504,
      "putGex": 0
    },
    {
      "strike": 7300,
      "netGex": 194116416,
      "callGex": 4220645131,
      "putGex": -4026528715
    },
    {
      "strike": 7305,
      "netGex": -77160514,
      "callGex": 57034788,
      "putGex": -134195302
    },
    {
      "strike": 7310,
      "netGex": 205387525,
      "callGex": 454944424,
      "putGex": -249556899
    },
    {
      "strike": 7315,
      "netGex": -95017335,
      "callGex": 51877582,
      "putGex": -146894916
    },
    {
      "strike": 7320,
      "netGex": 15741306,
      "callGex": 305922440,
      "putGex": -290181134
    },
    {
      "strike": 7325,
      "netGex": 436995200,
      "callGex": 1411124314,
      "putGex": -974129114
    },
    {
      "strike": 7330,
      "netGex": -162114108,
      "callGex": 313267830,
      "putGex": -475381937
    },
    {
      "strike": 7335,
      "netGex": -96203557,
      "callGex": 98848301,
      "putGex": -195051858
    },
    {
      "strike": 7340,
      "netGex": 16213610,
      "callGex": 676280665,
      "putGex": -660067054
    },
    {
      "strike": 7345,
      "netGex": -119464846,
      "callGex": 140560796,
      "putGex": -260025642
    },
    {
      "strike": 7350,
      "netGex": -247481849,
      "callGex": 2866237847,
      "putGex": -3113719696
    },
    {
      "strike": 7355,
      "netGex": -330275294,
      "callGex": 183487569,
      "putGex": -513762864
    },
    {
      "strike": 7360,
      "netGex": -142113647,
      "callGex": 617203307,
      "putGex": -759316954
    },
    {
      "strike": 7365,
      "netGex": -240655930,
      "callGex": 469157389,
      "putGex": -709813320
    },
    {
      "strike": 7370,
      "netGex": -27371632,
      "callGex": 913030177,
      "putGex": -940401810
    },
    {
      "strike": 7375,
      "netGex": 417193496,
      "callGex": 2505119463,
      "putGex": -2087925967
    },
    {
      "strike": 7380,
      "netGex": -125365599,
      "callGex": 602821072,
      "putGex": -728186671
    },
    {
      "strike": 7385,
      "netGex": -75291712,
      "callGex": 387520785,
      "putGex": -462812496
    },
    {
      "strike": 7390,
      "netGex": -274882699,
      "callGex": 755351273,
      "putGex": -1030233972
    },
    {
      "strike": 7395,
      "netGex": -45636004,
      "callGex": 568210069,
      "putGex": -613846073
    },
    {
      "strike": 7400,
      "netGex": 2698604387,
      "callGex": 10742704313,
      "putGex": -8044099926
    },
    {
      "strike": 7405,
      "netGex": 11142835,
      "callGex": 644467962,
      "putGex": -633325127
    },
    {
      "strike": 7410,
      "netGex": 520372290,
      "callGex": 1507852950,
      "putGex": -987480660
    },
    {
      "strike": 7415,
      "netGex": 44911829,
      "callGex": 892095365,
      "putGex": -847183536
    },
    {
      "strike": 7420,
      "netGex": 880273035,
      "callGex": 1895556086,
      "putGex": -1015283050
    },
    {
      "strike": 7425,
      "netGex": 1126528780,
      "callGex": 2783642044,
      "putGex": -1657113264
    },
    {
      "strike": 7430,
      "netGex": 1576987336,
      "callGex": 2266367203,
      "putGex": -689379866
    },
    {
      "strike": 7435,
      "netGex": 585337875,
      "callGex": 1390791408,
      "putGex": -805453533
    },
    {
      "strike": 7440,
      "netGex": 524074320,
      "callGex": 1503572603,
      "putGex": -979498282
    },
    {
      "strike": 7445,
      "netGex": 358573025,
      "callGex": 1113668448,
      "putGex": -755095423
    },
    {
      "strike": 7450,
      "netGex": 4767409743,
      "callGex": 7769423567,
      "putGex": -3002013823
    },
    {
      "strike": 7455,
      "netGex": 540607843,
      "callGex": 1110166684,
      "putGex": -569558841
    },
    {
      "strike": 7460,
      "netGex": 1351313828,
      "callGex": 1835174084,
      "putGex": -483860256
    },
    {
      "strike": 7465,
      "netGex": 783150948,
      "callGex": 1115789565,
      "putGex": -332638617
    },
    {
      "strike": 7470,
      "netGex": 2031750964,
      "callGex": 2685313168,
      "putGex": -653562203
    },
    {
      "strike": 7475,
      "netGex": 3562999103,
      "callGex": 5518786855,
      "putGex": -1955787752
    },
    {
      "strike": 7480,
      "netGex": 1903781891,
      "callGex": 2445764087,
      "putGex": -541982196
    },
    {
      "strike": 7485,
      "netGex": 1736209366,
      "callGex": 2059715697,
      "putGex": -323506330
    },
    {
      "strike": 7490,
      "netGex": 2856837350,
      "callGex": 3492103694,
      "putGex": -635266344
    },
    {
      "strike": 7495,
      "netGex": 1878966787,
      "callGex": 2257688473,
      "putGex": -378721685
    },
    {
      "strike": 7500,
      "netGex": 20624259968,
      "callGex": 26804188267,
      "putGex": -6179928299
    },
    {
      "strike": 7505,
      "netGex": 3514460511,
      "callGex": 3815400215,
      "putGex": -300939705
    },
    {
      "strike": 7510,
      "netGex": 2904982844,
      "callGex": 3394289074,
      "putGex": -489306230
    },
    {
      "strike": 7515,
      "netGex": 1420344687,
      "callGex": 1802601593,
      "putGex": -382256906
    },
    {
      "strike": 7520,
      "netGex": 3056931273,
      "callGex": 3442884415,
      "putGex": -385953143
    },
    {
      "strike": 7525,
      "netGex": 4558094989,
      "callGex": 5240488910,
      "putGex": -682393921
    },
    {
      "strike": 7530,
      "netGex": 1765779567,
      "callGex": 2352424501,
      "putGex": -586644934
    },
    {
      "strike": 7535,
      "netGex": 746227149,
      "callGex": 921663821,
      "putGex": -175436672
    },
    {
      "strike": 7540,
      "netGex": 2128042911,
      "callGex": 2211095611,
      "putGex": -83052701
    },
    {
      "strike": 7545,
      "netGex": 548063438,
      "callGex": 582694781,
      "putGex": -34631343
    },
    {
      "strike": 7550,
      "netGex": 4440772878,
      "callGex": 5041773644,
      "putGex": -601000766
    },
    {
      "strike": 7555,
      "netGex": 711554487,
      "callGex": 728484849,
      "putGex": -16930362
    },
    {
      "strike": 7560,
      "netGex": 1652350614,
      "callGex": 1697252216,
      "putGex": -44901602
    },
    {
      "strike": 7565,
      "netGex": 913881853,
      "callGex": 920211240,
      "putGex": -6329387
    },
    {
      "strike": 7570,
      "netGex": 1485070553,
      "callGex": 1553794914,
      "putGex": -68724362
    },
    {
      "strike": 7575,
      "netGex": 2882411745,
      "callGex": 3073087536,
      "putGex": -190675790
    },
    {
      "strike": 7580,
      "netGex": 1574753995,
      "callGex": 1610349413,
      "putGex": -35595418
    },
    {
      "strike": 7585,
      "netGex": 448400865,
      "callGex": 453324674,
      "putGex": -4923809
    },
    {
      "strike": 7590,
      "netGex": 615225675,
      "callGex": 667142449,
      "putGex": -51916773
    },
    {
      "strike": 7595,
      "netGex": 431236663,
      "callGex": 436149858,
      "putGex": -4913195
    },
    {
      "strike": 7600,
      "netGex": 7507862726,
      "callGex": 8613368936,
      "putGex": -1105506210
    },
    {
      "strike": 7605,
      "netGex": 738345342,
      "callGex": 741479691,
      "putGex": -3134349
    },
    {
      "strike": 7610,
      "netGex": 734096766,
      "callGex": 748104907,
      "putGex": -14008141
    },
    {
      "strike": 7615,
      "netGex": 237221752,
      "callGex": 241198167,
      "putGex": -3976415
    },
    {
      "strike": 7620,
      "netGex": 713345011,
      "callGex": 723979830,
      "putGex": -10634819
    },
    {
      "strike": 7625,
      "netGex": 1662871132,
      "callGex": 1780159738,
      "putGex": -117288606
    },
    {
      "strike": 7630,
      "netGex": 540015387,
      "callGex": 551985692,
      "putGex": -11970305
    },
    {
      "strike": 7635,
      "netGex": 218947713,
      "callGex": 221255706,
      "putGex": -2307993
    },
    {
      "strike": 7640,
      "netGex": 764361751,
      "callGex": 777207464,
      "putGex": -12845712
    },
    {
      "strike": 7645,
      "netGex": 177730068,
      "callGex": 180194115,
      "putGex": -2464047
    },
    {
      "strike": 7650,
      "netGex": 3577112780,
      "callGex": 3738157186,
      "putGex": -161044407
    },
    {
      "strike": 7655,
      "netGex": 128469250,
      "callGex": 129133964,
      "putGex": -664715
    },
    {
      "strike": 7660,
      "netGex": 299788920,
      "callGex": 318824184,
      "putGex": -19035264
    },
    {
      "strike": 7665,
      "netGex": 50882816,
      "callGex": 60389960,
      "putGex": -9507145
    },
    {
      "strike": 7670,
      "netGex": 266034089,
      "callGex": 268761514,
      "putGex": -2727425
    },
    {
      "strike": 7675,
      "netGex": 1636796751,
      "callGex": 1660010340,
      "putGex": -23213589
    },
    {
      "strike": 7680,
      "netGex": 373626949,
      "callGex": 377985946,
      "putGex": -4358997
    },
    {
      "strike": 7685,
      "netGex": 41522224,
      "callGex": 42962276,
      "putGex": -1440051
    },
    {
      "strike": 7690,
      "netGex": 238778700,
      "callGex": 257559389,
      "putGex": -18780689
    },
    {
      "strike": 7695,
      "netGex": 21553464,
      "callGex": 22555263,
      "putGex": -1001799
    },
    {
      "strike": 7700,
      "netGex": 1917536693,
      "callGex": 2120676299,
      "putGex": -203139606
    },
    {
      "strike": 7710,
      "netGex": 69180452,
      "callGex": 70049905,
      "putGex": -869453
    },
    {
      "strike": 7720,
      "netGex": 55858674,
      "callGex": 56380622,
      "putGex": -521948
    },
    {
      "strike": 7725,
      "netGex": 475515153,
      "callGex": 490361986,
      "putGex": -14846833
    },
    {
      "strike": 7730,
      "netGex": 17009451,
      "callGex": 17375283,
      "putGex": -365831
    },
    {
      "strike": 7740,
      "netGex": 28764005,
      "callGex": 29243015,
      "putGex": -479009
    },
    {
      "strike": 7750,
      "netGex": 710412915,
      "callGex": 757440875,
      "putGex": -47027961
    },
    {
      "strike": 7760,
      "netGex": 2937965,
      "callGex": 3625612,
      "putGex": -687646
    },
    {
      "strike": 7770,
      "netGex": 12232093,
      "callGex": 12667738,
      "putGex": -435644
    },
    {
      "strike": 7775,
      "netGex": 205352125,
      "callGex": 224555532,
      "putGex": -19203406
    },
    {
      "strike": 7780,
      "netGex": 2862649,
      "callGex": 2936724,
      "putGex": -74075
    },
    {
      "strike": 7790,
      "netGex": 1134929,
      "callGex": 1317328,
      "putGex": -182399
    },
    {
      "strike": 7800,
      "netGex": 900282388,
      "callGex": 1138704471,
      "putGex": -238422082
    },
    {
      "strike": 7810,
      "netGex": 1059351,
      "callGex": 1161205,
      "putGex": -101855
    },
    {
      "strike": 7820,
      "netGex": 2144064,
      "callGex": 2205323,
      "putGex": -61259
    },
    {
      "strike": 7825,
      "netGex": 329675230,
      "callGex": 339015964,
      "putGex": -9340735
    },
    {
      "strike": 7850,
      "netGex": 241851257,
      "callGex": 269326044,
      "putGex": -27474786
    }
  ],
  "events": [],
  "commentary": "**DEALER HEDGING COMMENTARY:**\n\nWith SPX at 7074 sitting below the 7099 flip strike in PIN regime, dealers are actively buying the dip as their long gamma position requires them to hedge by purchasing futures into weakness. The massive +6841M gamma wall at 7200 creates strong resistance where dealers will aggressively sell any rallies, while the -1078M negative gamma pocket at 7065 provides support through dealer buying. Key levels to watch: 7065 downside support, 7099 regime flip, and the heavy 7100/7150/7200 gamma wall cluster that should cap upside momentum.\n\n**Bottom line:** expect a bounce back toward 7100 with strong resistance at the 7150-7200 zone.",
  "updatedAt": "2026-05-22T17:47:06.748Z",
  "expiry": "2026-05-22:0",
  "expiryCount": 54,
  "dte": 0,
  "commentaryAt": "2026-04-21T18:16:46.857Z"
}