{
  "timestamp": 1780681862,
  "spot": 7452.93,
  "regime": "BREAKOUT",
  "totalGex": -46767887569,
  "totalCallGex": 116334122035,
  "totalPutGex": -163102009603,
  "flipStrike": 7100,
  "maxPosStrike": 7600,
  "maxPosGex": 3311455509,
  "maxNegStrike": 7450,
  "maxNegGex": -3603459546,
  "pctChange1m": 0.5,
  "pctChange5m": -0.8,
  "walls": [
    {
      "strike": 7450,
      "callGex": 7234402190,
      "putGex": -10837861736,
      "netGex": -3603459546,
      "callOI": 84472,
      "putOI": 71159,
      "direction": "amplifying"
    },
    {
      "strike": 7600,
      "callGex": 9816861138,
      "putGex": -6505405629,
      "netGex": 3311455509,
      "callOI": 182690,
      "putOI": 117361,
      "direction": "stabilizing"
    },
    {
      "strike": 7400,
      "callGex": 10556860302,
      "putGex": -13442739027,
      "netGex": -2885878725,
      "callOI": 161313,
      "putOI": 162633,
      "direction": "amplifying"
    },
    {
      "strike": 7650,
      "callGex": 3291784654,
      "putGex": -461222380,
      "netGex": 2830562274,
      "callOI": 76517,
      "putOI": 12526,
      "direction": "stabilizing"
    },
    {
      "strike": 7435,
      "callGex": 1044497864,
      "putGex": -3793429353,
      "netGex": -2748931489,
      "callOI": 7209,
      "putOI": 12562,
      "direction": "amplifying"
    },
    {
      "strike": 7460,
      "callGex": 804637758,
      "putGex": -3483763357,
      "netGex": -2679125600,
      "callOI": 6424,
      "putOI": 11061,
      "direction": "amplifying"
    },
    {
      "strike": 7415,
      "callGex": 929873812,
      "putGex": -3540275691,
      "netGex": -2610401879,
      "callOI": 8625,
      "putOI": 17852,
      "direction": "amplifying"
    },
    {
      "strike": 7300,
      "callGex": 3806094923,
      "putGex": -6391876192,
      "netGex": -2585781269,
      "callOI": 91360,
      "putOI": 138892,
      "direction": "amplifying"
    },
    {
      "strike": 7470,
      "callGex": 896969795,
      "putGex": -3326286829,
      "netGex": -2429317034,
      "callOI": 7387,
      "putOI": 12742,
      "direction": "amplifying"
    },
    {
      "strike": 7440,
      "callGex": 1068242737,
      "putGex": -3475503269,
      "netGex": -2407260531,
      "callOI": 7285,
      "putOI": 13008,
      "direction": "amplifying"
    }
  ],
  "strikes": [
    {
      "strike": 7100,
      "netGex": -62356828,
      "callGex": 390111029,
      "putGex": -452467857
    },
    {
      "strike": 7120,
      "netGex": -3841965,
      "callGex": 474317,
      "putGex": -4316281
    },
    {
      "strike": 7125,
      "netGex": -144921584,
      "callGex": 135156557,
      "putGex": -280078140
    },
    {
      "strike": 7130,
      "netGex": -2886465,
      "callGex": 2215743,
      "putGex": -5102208
    },
    {
      "strike": 7140,
      "netGex": -19860858,
      "callGex": 2933609,
      "putGex": -22794467
    },
    {
      "strike": 7150,
      "netGex": -200998792,
      "callGex": 372633745,
      "putGex": -573632537
    },
    {
      "strike": 7160,
      "netGex": -9996028,
      "callGex": 973768,
      "putGex": -10969796
    },
    {
      "strike": 7170,
      "netGex": -3789610,
      "callGex": 2960964,
      "putGex": -6750574
    },
    {
      "strike": 7175,
      "netGex": -204389055,
      "callGex": 119273094,
      "putGex": -323662149
    },
    {
      "strike": 7180,
      "netGex": -4997129,
      "callGex": 1421966,
      "putGex": -6419096
    },
    {
      "strike": 7190,
      "netGex": -8802326,
      "callGex": 597333,
      "putGex": -9399659
    },
    {
      "strike": 7200,
      "netGex": -173949174,
      "callGex": 1010595434,
      "putGex": -1184544608
    },
    {
      "strike": 7210,
      "netGex": -17560782,
      "callGex": 3147948,
      "putGex": -20708730
    },
    {
      "strike": 7220,
      "netGex": -24210555,
      "callGex": 2040706,
      "putGex": -26251261
    },
    {
      "strike": 7225,
      "netGex": -143735967,
      "callGex": 150750301,
      "putGex": -294486268
    },
    {
      "strike": 7230,
      "netGex": -39227215,
      "callGex": 3333584,
      "putGex": -42560799
    },
    {
      "strike": 7240,
      "netGex": -16769616,
      "callGex": 939907,
      "putGex": -17709523
    },
    {
      "strike": 7250,
      "netGex": -91190539,
      "callGex": 509248921,
      "putGex": -600439460
    },
    {
      "strike": 7255,
      "netGex": -225192256,
      "callGex": 148511887,
      "putGex": -373704143
    },
    {
      "strike": 7260,
      "netGex": -182367199,
      "callGex": 140221863,
      "putGex": -322589062
    },
    {
      "strike": 7265,
      "netGex": -63470508,
      "callGex": 143551603,
      "putGex": -207022111
    },
    {
      "strike": 7270,
      "netGex": -193900535,
      "callGex": 285433031,
      "putGex": -479333566
    },
    {
      "strike": 7275,
      "netGex": -575847785,
      "callGex": 791918697,
      "putGex": -1367766482
    },
    {
      "strike": 7280,
      "netGex": -261141582,
      "callGex": 484466057,
      "putGex": -745607639
    },
    {
      "strike": 7285,
      "netGex": -116140801,
      "callGex": 210804902,
      "putGex": -326945703
    },
    {
      "strike": 7290,
      "netGex": -204303081,
      "callGex": 284060275,
      "putGex": -488363355
    },
    {
      "strike": 7295,
      "netGex": -202203993,
      "callGex": 202243917,
      "putGex": -404447910
    },
    {
      "strike": 7300,
      "netGex": -2585781269,
      "callGex": 3806094923,
      "putGex": -6391876192
    },
    {
      "strike": 7305,
      "netGex": -102341285,
      "callGex": 38315111,
      "putGex": -140656396
    },
    {
      "strike": 7310,
      "netGex": -117277450,
      "callGex": 193240432,
      "putGex": -310517882
    },
    {
      "strike": 7315,
      "netGex": -316115590,
      "callGex": 47748076,
      "putGex": -363863666
    },
    {
      "strike": 7320,
      "netGex": -106821668,
      "callGex": 225180549,
      "putGex": -332002217
    },
    {
      "strike": 7325,
      "netGex": -39607094,
      "callGex": 1164686126,
      "putGex": -1204293220
    },
    {
      "strike": 7330,
      "netGex": -284187978,
      "callGex": 294248892,
      "putGex": -578436870
    },
    {
      "strike": 7335,
      "netGex": -681832178,
      "callGex": 40287891,
      "putGex": -722120069
    },
    {
      "strike": 7340,
      "netGex": -431816105,
      "callGex": 419882985,
      "putGex": -851699089
    },
    {
      "strike": 7345,
      "netGex": -316857204,
      "callGex": 135864525,
      "putGex": -452721729
    },
    {
      "strike": 7350,
      "netGex": -1443561601,
      "callGex": 2841886402,
      "putGex": -4285448003
    },
    {
      "strike": 7355,
      "netGex": -539187871,
      "callGex": 154778431,
      "putGex": -693966302
    },
    {
      "strike": 7360,
      "netGex": -158205671,
      "callGex": 645870175,
      "putGex": -804075847
    },
    {
      "strike": 7365,
      "netGex": -337386621,
      "callGex": 549288653,
      "putGex": -886675274
    },
    {
      "strike": 7370,
      "netGex": -966551328,
      "callGex": 993622505,
      "putGex": -1960173833
    },
    {
      "strike": 7375,
      "netGex": -1617493593,
      "callGex": 2462087860,
      "putGex": -4079581453
    },
    {
      "strike": 7380,
      "netGex": -1331459275,
      "callGex": 568770123,
      "putGex": -1900229398
    },
    {
      "strike": 7385,
      "netGex": -2129281233,
      "callGex": 381408235,
      "putGex": -2510689468
    },
    {
      "strike": 7390,
      "netGex": -1873027835,
      "callGex": 766656909,
      "putGex": -2639684744
    },
    {
      "strike": 7395,
      "netGex": -1095785759,
      "callGex": 511274610,
      "putGex": -1607060370
    },
    {
      "strike": 7400,
      "netGex": -2885878725,
      "callGex": 10556860302,
      "putGex": -13442739027
    },
    {
      "strike": 7405,
      "netGex": -989121460,
      "callGex": 631754504,
      "putGex": -1620875964
    },
    {
      "strike": 7410,
      "netGex": -1577958661,
      "callGex": 962441477,
      "putGex": -2540400138
    },
    {
      "strike": 7415,
      "netGex": -2610401879,
      "callGex": 929873812,
      "putGex": -3540275691
    },
    {
      "strike": 7420,
      "netGex": -1568862222,
      "callGex": 1222039967,
      "putGex": -2790902190
    },
    {
      "strike": 7425,
      "netGex": -1422037884,
      "callGex": 2388715658,
      "putGex": -3810753542
    },
    {
      "strike": 7430,
      "netGex": -823345142,
      "callGex": 2348241152,
      "putGex": -3171586294
    },
    {
      "strike": 7435,
      "netGex": -2748931489,
      "callGex": 1044497864,
      "putGex": -3793429353
    },
    {
      "strike": 7440,
      "netGex": -2407260531,
      "callGex": 1068242737,
      "putGex": -3475503269
    },
    {
      "strike": 7445,
      "netGex": -1637406591,
      "callGex": 703577888,
      "putGex": -2340984479
    },
    {
      "strike": 7450,
      "netGex": -3603459546,
      "callGex": 7234402190,
      "putGex": -10837861736
    },
    {
      "strike": 7455,
      "netGex": -1329020115,
      "callGex": 659085197,
      "putGex": -1988105311
    },
    {
      "strike": 7460,
      "netGex": -2679125600,
      "callGex": 804637758,
      "putGex": -3483763357
    },
    {
      "strike": 7465,
      "netGex": -2150639854,
      "callGex": 418822740,
      "putGex": -2569462594
    },
    {
      "strike": 7470,
      "netGex": -2429317034,
      "callGex": 896969795,
      "putGex": -3326286829
    },
    {
      "strike": 7475,
      "netGex": -1008943431,
      "callGex": 2729940831,
      "putGex": -3738884262
    },
    {
      "strike": 7480,
      "netGex": -1682270394,
      "callGex": 816601583,
      "putGex": -2498871977
    },
    {
      "strike": 7485,
      "netGex": -1901523798,
      "callGex": 337719453,
      "putGex": -2239243251
    },
    {
      "strike": 7490,
      "netGex": -965473674,
      "callGex": 987954535,
      "putGex": -1953428208
    },
    {
      "strike": 7495,
      "netGex": -1189448237,
      "callGex": 575055886,
      "putGex": -1764504123
    },
    {
      "strike": 7500,
      "netGex": -452281979,
      "callGex": 11378789073,
      "putGex": -11831071052
    },
    {
      "strike": 7505,
      "netGex": -540735535,
      "callGex": 649602126,
      "putGex": -1190337661
    },
    {
      "strike": 7510,
      "netGex": -425485860,
      "callGex": 890311517,
      "putGex": -1315797377
    },
    {
      "strike": 7515,
      "netGex": -336761933,
      "callGex": 761696522,
      "putGex": -1098458455
    },
    {
      "strike": 7520,
      "netGex": -339065563,
      "callGex": 948042189,
      "putGex": -1287107752
    },
    {
      "strike": 7525,
      "netGex": 507278505,
      "callGex": 2941238505,
      "putGex": -2433960000
    },
    {
      "strike": 7530,
      "netGex": -781681495,
      "callGex": 1290054484,
      "putGex": -2071735979
    },
    {
      "strike": 7535,
      "netGex": -214136947,
      "callGex": 692108553,
      "putGex": -906245501
    },
    {
      "strike": 7540,
      "netGex": -237515704,
      "callGex": 958885946,
      "putGex": -1196401651
    },
    {
      "strike": 7545,
      "netGex": -183990616,
      "callGex": 506357620,
      "putGex": -690348236
    },
    {
      "strike": 7550,
      "netGex": 694957370,
      "callGex": 5599166694,
      "putGex": -4904209324
    },
    {
      "strike": 7555,
      "netGex": -170368293,
      "callGex": 428689954,
      "putGex": -599058247
    },
    {
      "strike": 7560,
      "netGex": 100914758,
      "callGex": 848426432,
      "putGex": -747511674
    },
    {
      "strike": 7565,
      "netGex": -56472995,
      "callGex": 447259544,
      "putGex": -503732539
    },
    {
      "strike": 7570,
      "netGex": 20168628,
      "callGex": 621815213,
      "putGex": -601646585
    },
    {
      "strike": 7575,
      "netGex": 1238637839,
      "callGex": 2758957367,
      "putGex": -1520319528
    },
    {
      "strike": 7580,
      "netGex": 115524976,
      "callGex": 1074037604,
      "putGex": -958512627
    },
    {
      "strike": 7585,
      "netGex": 6065505,
      "callGex": 970623089,
      "putGex": -964557583
    },
    {
      "strike": 7590,
      "netGex": -8330529,
      "callGex": 1131817215,
      "putGex": -1140147744
    },
    {
      "strike": 7595,
      "netGex": 50967622,
      "callGex": 768624288,
      "putGex": -717656665
    },
    {
      "strike": 7600,
      "netGex": 3311455509,
      "callGex": 9816861138,
      "putGex": -6505405629
    },
    {
      "strike": 7605,
      "netGex": 165891728,
      "callGex": 575087725,
      "putGex": -409195997
    },
    {
      "strike": 7610,
      "netGex": 325713682,
      "callGex": 721779366,
      "putGex": -396065684
    },
    {
      "strike": 7615,
      "netGex": 237482258,
      "callGex": 470191285,
      "putGex": -232709027
    },
    {
      "strike": 7620,
      "netGex": 266621843,
      "callGex": 560233945,
      "putGex": -293612102
    },
    {
      "strike": 7625,
      "netGex": 962761882,
      "callGex": 1708774303,
      "putGex": -746012420
    },
    {
      "strike": 7630,
      "netGex": 344117477,
      "callGex": 555874715,
      "putGex": -211757238
    },
    {
      "strike": 7635,
      "netGex": 96695589,
      "callGex": 129193301,
      "putGex": -32497712
    },
    {
      "strike": 7640,
      "netGex": 395822824,
      "callGex": 502469676,
      "putGex": -106646852
    },
    {
      "strike": 7645,
      "netGex": 132884314,
      "callGex": 160778073,
      "putGex": -27893759
    },
    {
      "strike": 7650,
      "netGex": 2830562274,
      "callGex": 3291784654,
      "putGex": -461222380
    },
    {
      "strike": 7660,
      "netGex": 11517731,
      "callGex": 15812892,
      "putGex": -4295161
    },
    {
      "strike": 7670,
      "netGex": 4612041,
      "callGex": 7466807,
      "putGex": -2854766
    },
    {
      "strike": 7675,
      "netGex": 188891035,
      "callGex": 227130493,
      "putGex": -38239458
    },
    {
      "strike": 7680,
      "netGex": 39223977,
      "callGex": 40385531,
      "putGex": -1161554
    },
    {
      "strike": 7690,
      "netGex": 3538809,
      "callGex": 4335545,
      "putGex": -796736
    },
    {
      "strike": 7700,
      "netGex": 698590180,
      "callGex": 994049209,
      "putGex": -295459030
    },
    {
      "strike": 7710,
      "netGex": 13823144,
      "callGex": 14206310,
      "putGex": -383166
    },
    {
      "strike": 7720,
      "netGex": 2378401,
      "callGex": 4763117,
      "putGex": -2384716
    },
    {
      "strike": 7725,
      "netGex": 198553380,
      "callGex": 231615416,
      "putGex": -33062037
    },
    {
      "strike": 7730,
      "netGex": 8307023,
      "callGex": 13082521,
      "putGex": -4775499
    },
    {
      "strike": 7740,
      "netGex": 6543288,
      "callGex": 7364795,
      "putGex": -821507
    },
    {
      "strike": 7750,
      "netGex": 374690605,
      "callGex": 466398037,
      "putGex": -91707432
    },
    {
      "strike": 7760,
      "netGex": 2895342,
      "callGex": 4398474,
      "putGex": -1503132
    },
    {
      "strike": 7770,
      "netGex": 14108275,
      "callGex": 14742417,
      "putGex": -634141
    },
    {
      "strike": 7775,
      "netGex": 123256687,
      "callGex": 152258281,
      "putGex": -29001594
    },
    {
      "strike": 7780,
      "netGex": 2529773,
      "callGex": 2699986,
      "putGex": -170212
    },
    {
      "strike": 7800,
      "netGex": 658606089,
      "callGex": 900792556,
      "putGex": -242186466
    },
    {
      "strike": 7825,
      "netGex": 105406617,
      "callGex": 114437632,
      "putGex": -9031014
    }
  ],
  "events": [],
  "commentary": "**DEALER HEDGING COMMENTARY:**\n\nWith SPX at 7074 sitting below the 7099 flip strike in PIN regime, dealers are actively buying the dip as their long gamma position requires them to hedge by purchasing futures into weakness. The massive +6841M gamma wall at 7200 creates strong resistance where dealers will aggressively sell any rallies, while the -1078M negative gamma pocket at 7065 provides support through dealer buying. Key levels to watch: 7065 downside support, 7099 regime flip, and the heavy 7100/7150/7200 gamma wall cluster that should cap upside momentum.\n\n**Bottom line:** expect a bounce back toward 7100 with strong resistance at the 7150-7200 zone.",
  "updatedAt": "2026-06-05T17:51:02.985Z",
  "expiry": "2026-06-05:0",
  "expiryCount": 54,
  "dte": 0,
  "commentaryAt": "2026-04-21T18:16:46.857Z"
}